{
  "project_info": {
    "project_number": "1062390183239",
    "project_id": "amerschool-43c35",
    "storage_bucket": "amerschool-43c35.appspot.com"
  },
  "client": [
    {
      "client_info": {
        "mobilesdk_app_id": "1:1062390183239:android:5e382a44ea2c58c7ecc862",
        "android_client_info": {
          "package_name": "com.example.amer_school"
        }
      },
      "oauth_client": [
        {
          "client_id": "1062390183239-2jn9t78kdiiktmdm5mu6rf0ukcpum813.apps.googleusercontent.com",
          "client_type": 3
        }
      ],
      "api_key": [
        {
          "current_key": "AIzaSyDSxFsRCeGB3c7kZs9K7MVgfHmLg1lYRx4"
        }
      ],
      "services": {
        "appinvite_service": {
          "other_platform_oauth_client": [
            {
              "client_id": "1062390183239-2jn9t78kdiiktmdm5mu6rf0ukcpum813.apps.googleusercontent.com",
              "client_type": 3
            }
          ]
        }
      }
    }
  ],
  "configuration_version": "1"
}